{"published_database_解决redis连接报错_err max number of clients reached_.md":"0b5f0c6b","published_database_clickhouse报错解决.md":"f0f261c3","published_database_postgres配置参数优化.md":"78f6ac78","index.md":"6a7222cc","published_ip配置时候需要注意点.md":"7714fd7c","published_monitor-collector_redfish介绍与使用.md":"be2d0934","published_database_数据库优化器与算子.md":"f1ad4211","published_golang安装配置与docker构建.md":"35af449f","published_libreoffice使用命令行更新目录.md":"9d6b8eaa","published_monitor-collector_apache服务资源监控.md":"43aeba9d","published_monitor-collector_nginx服务资源监控.md":"5e5d14d7","published_database_apachearrow-datafusion查询引擎.md":"37b54a2e","published_system_docker容器操作宿主机执行命令.md":"7e2083ff","published_system_freebsd配置服务开机自启动.md":"928e2471","published_grpc理解与使用.md":"97528f72","published_database_apachearrow-parquet存储.md":"66c73cbe","published_rust_使用rust开发android底层.md":"83f05100","published_system_无外网情况下的centos软件安装.md":"33e144ab","published_ubuntu下的docker和docker-compose安装.md":"01fb1528","published_system_macos使用launchd管理后台服务.md":"bd47c4df","published_drf-yasg打开文档速度很慢的解决方案.md":"c5d10e6f","rust-setup.md":"5d4de7a8","published_monitor-collector_容器环境下使用glances监控系统资源.md":"8cf0a494","published_身份认证_jwt身份认证概述.md":"ff8e6d51","published_database_clickhouse查询性能优化.md":"7e6a0c03","published_monitor-collector_基于docker-compose搭建prometheus与grafana环境.md":"93745824","published_rust_关于rust交叉编译的问题.md":"1e54f4bd","published_python操作docker kafka.md":"3a364df1","published_身份认证_ubuntu系统下的radius认证服务安装与配置.md":"7fd170e6","published_算法_国产加密算法概述与应用.md":"e1242d3e","published_monitor-collector_不同操作系统日志获取.md":"bf93dd6b","published_system_python项目适配arm架构国产麒麟系统.md":"78ce11a2","published_powershell配置utf-8编码.md":"43623991","rust项目优化小册与常用库.md":"7e9ba7e5","published_system_debian与ubuntu系列的桌面安装与卸载.md":"d914f76f","published_算法_区块链常见共识算法概述.md":"41a3159c","published_monitor-collector_网络流协议sflow详解与使用.md":"4df7d934","计划项.md":"435a714c","published_database_apachearrow-入门介绍.md":"8e3a1e2e","published_system_安卓手机安装magisk.md":"3cead5b7","published_monitor-collector_linux获取存储设备信息.md":"93d77ad6","published_ubuntu环境下配置snmp.md":"059c1f8d","published_system_systemd详解与使用.md":"f7dfe08a","published_常用负载均衡方案概述.md":"13d02a90","published_system_微服务与服务网格istio的简介与使用.md":"ed787672","published_ubuntu下面vmware模块安装失败.md":"9b619696","published_system_k8s访问集群外部服务.md":"2f9fa480","published_monitor-collector_网络流协议netflow与ipfix详解与使用采集.md":"1d024b4b","published_rust_rust使用hashmap存储函数并调用.md":"376b3bc5","published_monitor-collector_配置kvm虚拟交换机网口以及开启snmp服务.md":"1d06b30f","published_system_使用rke2搭建k8s集群.md":"aa85cb31","published_python项目编译加密.md":"f97d3e68","published_net-snmp静态编译.md":"97b6bae0","published_rust_rust二进制文件大小优化.md":"84d1bb15","published_database_postgresql的增量备份与恢复.md":"10094825","published_monitor-collector_linux硬件性能评估.md":"5e343a5f"}
